Metadata-Version: 2.1
Name: schemaser
Version: 1.0.1
Summary: Converts a Python class or method to a JSON schema.
Home-page: https://github.com/legopitstop/schemaser
Author: Legopitstop
Author-email: officiallegopitstop@gmail.com
License: MIT
Keywords: json,jsonschema,schema,class,method
Classifier: Development Status :: 5 - Production/Stable
Classifier: Intended Audience :: Developers
Classifier: Topic :: Software Development :: Build Tools
Classifier: License :: OSI Approved :: MIT License
Classifier: Operating System :: Microsoft :: Windows
Classifier: Programming Language :: Python :: 3.9
Requires-Python: >=3.6
License-File: LICENSE
